AUTHORS
HISTORY.rst
LICENSE
MANIFEST.in
README.rst
requirements.txt
setup.cfg
setup.py
requests_gssapi/__init__.py
requests_gssapi/compat.py
requests_gssapi/exceptions.py
requests_gssapi/gssapi_.py
requests_gssapi.egg-info/PKG-INFO
requests_gssapi.egg-info/SOURCES.txt
requests_gssapi.egg-info/dependency_links.txt
requests_gssapi.egg-info/requires.txt
requests_gssapi.egg-info/top_level.txt