Metadata-Version: 1.1
Name: requests-gssapi
Version: 1.0.1
Summary: A GSSAPI authentication handler for python-requests
Home-page: https://github.com/pythongssapi/requests-gssapi
Author: Ian Cordasco, Cory Benfield, Michael Komitee, Robbie Harwood
Author-email: rharwood@redhat.com
License: UNKNOWN
Platform: UNKNOWN
Classifier: License :: OSI Approved :: ISC License (ISCL)
